corpse/__init__.py
corpse-0.0.0.dist-info/METADATA
corpse-0.0.0.dist-info/WHEEL
corpse-0.0.0.dist-info/top_level.txt
corpse-0.0.0.dist-info/RECORD
