Metadata-Version: 2.1
Name: corpse
Version: 0.0.0
Summary: Package reservation
Home-page: https://github.com/zyronix/corpse
Author: Romke van Dijk
Author-email: mail+pypi@ocbios.nl
License: UNKNOWN
Platform: UNKNOWN
Classifier: Development Status :: 1 - Planning
Classifier: Programming Language :: Python :: 3.6
Classifier: Operating System :: POSIX :: Linux
